swimmer_time/__init__.py
swimmer_time/cli.py
swimmer_time/py.typed
swimmer_time/scraper.py
swimmer_time-0.1.0.dist-info/LICENSE
swimmer_time-0.1.0.dist-info/METADATA
swimmer_time-0.1.0.dist-info/WHEEL
swimmer_time-0.1.0.dist-info/entry_points.txt
swimmer_time-0.1.0.dist-info/RECORD
