Metadata-Version: 2.3
Name: swimmer-time
Version: 0.1.0
Summary: A package to scrape swimmer time data from USA Swimming
License: MIT
Keywords: swimming,usa-swimming,scraper,selenium,data
Author: Kevin Wang
Requires-Python: >=3.8,<4.0
Classifier: Development Status :: 4 - Beta
Classifier: Intended Audience :: Developers
Classifier: License :: OSI Approved :: MIT License
Classifier: Programming Language :: Python :: 3
Classifier: Programming Language :: Python :: 3.8
Classifier: Programming Language :: Python :: 3.9
Classifier: Programming Language :: Python :: 3.10
Classifier: Programming Language :: Python :: 3.11
Classifier: Programming Language :: Python :: 3.12
Classifier: Programming Language :: Python :: 3.13
Classifier: Topic :: Internet :: WWW/HTTP :: Dynamic Content
Classifier: Topic :: Software Development :: Libraries :: Python Modules
Requires-Dist: pandas (>=2.0.0,<3.0.0)
Requires-Dist: pyyaml (>=6.0,<7.0)
Requires-Dist: selenium (>=4.0.0,<5.0.0)
Project-URL: Bug Tracker, https://github.com/kevinwangDFS/swimmer-time-usaswim/issues
Project-URL: Repository, https://github.com/kevinwangDFS/swimmer-time-usaswim
